tale/__init__.py
tale/accounts.py
tale/author.py
tale/base.py
tale/charbuilder.py
tale/driver.py
tale/driver_if.py
tale/driver_mud.py
tale/errors.py
tale/lang.py
tale/main.py
tale/player.py
tale/pubsub.py
tale/races.py
tale/savegames.py
tale/shop.py
tale/soul_adverbs.txt
tale/story.py
tale/util.py
tale/verbdefs.py
tale/vfs.py
tale/authoring/house_tpl.py
tale/authoring/main_tpl.py
tale/authoring/story_tpl.py
tale/cmds/__init__.py
tale/cmds/normal.py
tale/cmds/wizard.py
tale/demo/__init__.py
tale/demo/story.py
tale/demo/zones/__init__.py
tale/demo/zones/house.py
tale/items/__init__.py
tale/items/bank.py
tale/items/basic.py
tale/items/board.py
tale/tio/__init__.py
tale/tio/colorama_patched.py
tale/tio/console_io.py
tale/tio/if_browser_io.py
tale/tio/iobase.py
tale/tio/mud_browser_io.py
tale/tio/quill_pen_paper.gif
tale/tio/quill_pen_paper.ico
tale/tio/styleaware_wrapper.py
tale/tio/tkinter_io.py
tale/web/about.html
tale/web/about_license.html
tale/web/about_mud.html
tale/web/eventsource.js
tale/web/eventsource.min.js
tale/web/favicon.ico
tale/web/index.html
tale/web/logo.gif
tale/web/normalize.css
tale/web/script.js
tale/web/story.html
tale/web/style.css
tale-4.7.data/scripts/tale-run
tale-4.7.data/scripts/tale-run.cmd
tale-4.7.dist-info/LICENSE.txt
tale-4.7.dist-info/METADATA
tale-4.7.dist-info/WHEEL
tale-4.7.dist-info/top_level.txt
tale-4.7.dist-info/zip-safe
tale-4.7.dist-info/RECORD
