Metadata-Version: 2.1
Name: tale
Version: 4.7
Summary: Interactive Fiction, MUD & mudlib framework
Home-page: http://tale.readthedocs.io/
Author: Irmen de Jong
Author-email: irmen@razorvine.net
License: LGPL3
Keywords: mud,mudlib,interactive fiction,text adventure
Platform: any
Classifier: Development Status :: 4 - Beta
Classifier: Environment :: Console
Classifier: Intended Audience :: Developers
Classifier: Intended Audience :: End Users/Desktop
Classifier: License :: OSI Approved :: GNU Lesser General Public License v3 (LGPLv3)
Classifier: Natural Language :: English
Classifier: Operating System :: OS Independent
Classifier: Programming Language :: Python
Classifier: Programming Language :: Python :: 3
Classifier: Programming Language :: Python :: 3.5
Classifier: Programming Language :: Python :: 3.6
Classifier: Programming Language :: Python :: 3.7
Classifier: Programming Language :: Python :: 3.8
Classifier: Topic :: Communications :: Chat
Classifier: Topic :: Games/Entertainment
Classifier: Topic :: Games/Entertainment :: Role-Playing
Classifier: Topic :: Games/Entertainment :: Multi-User Dungeons (MUD)
Requires-Dist: appdirs
Requires-Dist: colorama (>=0.3.6)
Requires-Dist: smartypants (>=1.8.6)
Requires-Dist: serpent (>=1.23)
